{
  "house": {
    "facilities": [
      {
        "value": 1,
        "label": "电视机",
        "icon": ""
      },
      {
        "value": 2,
        "label": "洗衣机",
        "icon": ""
      },
      {
        "value": 3,
        "label": "冰箱",
        "icon": ""
      },
      {
        "value": 4,
        "label": "沙发",
        "icon": ""
      },
      {
        "value": 5,
        "label": "床",
        "icon": ""
      },
      {
        "value": 6,
        "label": "宽带",
        "icon": ""
      },
      {
        "value": 7,
        "label": "电脑桌",
        "icon": "",
        "disabled": false
      },
      {
        "value": 8,
        "label": "衣柜",
        "icon": ""
      },
      {
        "value": 9,
        "label": "静音空调",
        "icon": ""
      },
      {
        "value": 10,
        "label": "普通空调",
        "icon": ""
      }
    ],
    "trade": [
      {
        "label": "出租",
        "value": "rent"
      },
      {
        "label": "出售",
        "value": "sale"
      }
    ],
    "type": [
      {
        "label": "公寓",
        "value": "apartment"
      },
      {
        "label": "别墅",
        "value": "villa"
      },
      {
        "label": "民宿",
        "value": "homestay"
      },
      {
        "label": "商铺/写字楼",
        "value": "office"
      },
      {
        "label": "公寓",
        "value": "carport"
      }
    ],
    "purpose": [
      {
        "label": "办公",
        "value": "office"
      },
      {
        "label": "居住",
        "value": "live"
      },
      {
        "label": "商住两用",
        "value": "office_live"
      }
    ],
    "rent_type":[
      {
        "label": "整租",
        "value": "sole"
      },
      {
        "label": "合租",
        "value": "shared"
      }
    ],
    "decor":[
      {
        "label": "精装修",
        "value": "1"
      },
      {
        "label": "豪华装修",
        "value": "2"
      },
      {
        "label": "毛坯",
        "value": "3"
      }
    ],
    "master_direction":[
      {
        "label": "东",
        "value": "1"
      },
      {
        "label": "西",
        "value": "2"
      },
      {
        "label": "南",
        "value": "3"
      },
      {
        "label": "北",
        "value": "4"
      }
    ]
  },
  "user": {
    "gender": [
      {
        "label": "男",
        "value": "1"
      },
      {
        "label": "女",
        "value": "2"
      },
      {
        "label": "其他",
        "value": "3"
      }
    ]
  }
}